funniest/__init__.py
funniest-david-brakman/__init__.py
funniest-david-brakman/text.py
funniest_david_brakman-0.2.dist-info/DESCRIPTION.rst
funniest_david_brakman-0.2.dist-info/METADATA
funniest_david_brakman-0.2.dist-info/RECORD
funniest_david_brakman-0.2.dist-info/WHEEL
funniest_david_brakman-0.2.dist-info/metadata.json
funniest_david_brakman-0.2.dist-info/top_level.txt
