Metadata-Version: 2.0
Name: funniest-david-brakman
Version: 0.2
Summary: The funniest joke in the world
Home-page: http://github.com/storborg/funniest
Author: Flying Circus
Author-email: flyingcircus@example.com
License: MIT
Platform: UNKNOWN
Requires-Dist: markdown
